devopso_credentials_manager/plugin.py
devops_overseer_credentials-0.1.2.dist-info/METADATA
devops_overseer_credentials-0.1.2.dist-info/WHEEL
devops_overseer_credentials-0.1.2.dist-info/entry_points.txt
devops_overseer_credentials-0.1.2.dist-info/top_level.txt
devops_overseer_credentials-0.1.2.dist-info/RECORD
