Metadata-Version: 2.4
Name: devops-overseer-credentials
Version: 0.1.2
Summary: A basic Python plugin
Author-email: mot0ko <dourval.clement@gmail.com>
Requires-Python: >=3.8
Requires-Dist: devops-overseer>=0.0.3
